julian/_DEPRECATED.py
julian/_TIMEZONES.py
julian/__init__.py
julian/_deltat.py
julian/_exceptions.py
julian/_utils.py
julian/_version.py
julian/_warnings.py
julian/calendar.py
julian/date_parsers.py
julian/date_pyparser.py
julian/datetime_parsers.py
julian/datetime_pyparser.py
julian/formatters.py
julian/iso_parsers.py
julian/leap_seconds.py
julian/mjd_jd.py
julian/mjd_pyparser.py
julian/time_of_day.py
julian/time_parsers.py
julian/time_pyparser.py
julian/utc_tai_tdb_tt.py
julian/assets/naif0012.tls
rms_julian-3.0.1.dist-info/licenses/LICENSE
rms_julian-3.0.1.dist-info/METADATA
rms_julian-3.0.1.dist-info/WHEEL
rms_julian-3.0.1.dist-info/top_level.txt
rms_julian-3.0.1.dist-info/RECORD
