Metadata-Version: 2.4
Name: rms-julian
Version: 3.0.1
Summary: Tools for astronomical time systems, supporting array operations, leap seconds, date/time parsing, and formatting
Maintainer-email: "Robert S. French" <rfrench@seti.org>
License: Apache-2.0
Project-URL: Homepage, https://github.com/SETI/rms-julian
Project-URL: Documentation, https://rms-julian.readthedocs.io/en/latest
Project-URL: Repository, https://github.com/SETI/rms-julian
Project-URL: Source, https://github.com/SETI/rms-julian
Project-URL: Issues, https://github.com/SETI/rms-julian/issues
Keywords: julian
Classifier: Development Status :: 5 - Production/Stable
Classifier: Natural Language :: English
Classifier: Topic :: Scientific/Engineering
Classifier: Topic :: Scientific/Engineering :: Astronomy
Classifier: Topic :: Software Development :: Libraries :: Python Modules
Classifier: Topic :: Utilities
Classifier: License :: OSI Approved :: Apache Software License
Classifier: Programming Language :: Python :: 3.9
Classifier: Programming Language :: Python :: 3.10
Classifier: Programming Language :: Python :: 3.11
Classifier: Programming Language :: Python :: 3.12
Classifier: Programming Language :: Python :: 3.13
Classifier: Operating System :: MacOS :: MacOS X
Classifier: Operating System :: POSIX :: Linux
Classifier: Operating System :: Microsoft :: Windows
Requires-Python: >=3.9
License-File: LICENSE
Requires-Dist: numpy
Requires-Dist: pyparsing
Requires-Dist: rms-filecache
Requires-Dist: rms-textkernel
Dynamic: license-file
